deriva/__init__.py
deriva/qt/__init__.py
deriva/qt/auth_agent/__init__.py
deriva/qt/auth_agent/__main__.py
deriva/qt/auth_agent/resources/__init__.py
deriva/qt/auth_agent/resources/resources.py
deriva/qt/auth_agent/resources/images/keys.icns
deriva/qt/auth_agent/resources/images/keys.ico
deriva/qt/auth_agent/resources/images/keys.png
deriva/qt/auth_agent/ui/__init__.py
deriva/qt/auth_agent/ui/auth_widget.py
deriva/qt/auth_agent/ui/auth_window.py
deriva/qt/auth_agent/ui/embedded_auth_window.py
deriva/qt/common/__init__.py
deriva/qt/common/async_task.py
deriva/qt/common/json_editor.py
deriva/qt/common/log_widget.py
deriva/qt/common/table_widget.py
deriva/qt/upload_gui/__init__.py
deriva/qt/upload_gui/__main__.py
deriva/qt/upload_gui/deriva_upload_gui.py
deriva/qt/upload_gui/conf/config.json
deriva/qt/upload_gui/impl/__init__.py
deriva/qt/upload_gui/impl/upload_tasks.py
deriva/qt/upload_gui/resources/__init__.py
deriva/qt/upload_gui/resources/resources.py
deriva/qt/upload_gui/resources/images/upload.icns
deriva/qt/upload_gui/resources/images/upload.ico
deriva/qt/upload_gui/resources/images/upload.png
deriva/qt/upload_gui/ui/__init__.py
deriva/qt/upload_gui/ui/options_window.py
deriva/qt/upload_gui/ui/upload_window.py
deriva_qt-1.7.9.dist-info/licenses/LICENSE
deriva_qt-1.7.9.dist-info/METADATA
deriva_qt-1.7.9.dist-info/WHEEL
deriva_qt-1.7.9.dist-info/entry_points.txt
deriva_qt-1.7.9.dist-info/top_level.txt
deriva_qt-1.7.9.dist-info/RECORD
